{
  "date": "2026-06-21T12:34:14.921305+00:00",
  "timestamp": 1782045254.921305,
  "street_rate_bob": 9.96,
  "official_rates": {
    "GBP": 1.0,
    "USD": 1.316001,
    "EUR": 1.151278,
    "AUD": 1.8799,
    "CAD": 1.8629,
    "TWD": 41.585229,
    "JPY": 211.850942,
    "CNY": 8.90748,
    "RUB": 96.029193,
    "BOB": 9.027764,
    "NZD": 2.282347,
    "CHF": 1.0598,
    "SGD": 1.694614,
    "HKD": 10.31166,
    "SEK": 12.6247,
    "NOK": 12.771996,
    "DKK": 8.597698,
    "MXN": 22.77894,
    "KRW": 2006.823199,
    "ILS": 3.860883
  },
  "base": "GBP",
  "source": "scraped_monzo",
  "currency_pair": "USD_to_BOB_Cash_Sell"
}